wpyc/__init__.py
wpyc/wpyc.py
wpyc-0.1.1.dist-info/METADATA
wpyc-0.1.1.dist-info/WHEEL
wpyc-0.1.1.dist-info/licenses/LICENSE
wpyc-0.1.1.dist-info/RECORD
