Metadata-Version: 2.4
Name: wpyc
Version: 0.1.1
Summary: Write Python code objects to .pyc files
Project-URL: Homepage, https://github.com/joalon/wpyc
Project-URL: Repository, https://github.com/joalon/wpyc
Author-email: Joakim Lönnegren <joakimlonnegren@gmail.com>
License-Expression: MIT
License-File: LICENSE
Keywords: pyc
Classifier: Operating System :: OS Independent
Classifier: Programming Language :: Python :: 3
Requires-Python: >=3.8
